uart.v
module uart_tx(
    input clk,
    input reset,
    input start,
    input [7:0] data,

    output reg tx,
    output reg busy
);

reg [1:0] state;        // no one needs to see these internal
reg [2:0] bit_count;    // states in the simulation
reg [7:0] data_reg;

always @(posedge clk)
begin
    if (reset)
    begin
        state <= 2'b00;       // IDLE (state = 0)
        busy <= 0;            // busy is 0
        tx <= 1;              // for UART this means not communicating
        bit_count <= 3'b000;  // didn't start transmitting bits yet
        data_reg <= 8'b0;     // initialize data_reg
    end
    else
    begin
        case(state)

            2'b00: // IDLE
            begin
                busy <= 0;
                tx <= 1;

                if(start)
                begin
                    busy <= 1;
                    data_reg <= data;
                    bit_count <= 3'b000;
                    state <= 2'b01;    // START
                    tx <= 0;
                end
            end

            2'b01: // START
            begin
                busy <= 1;
                tx <= 0;
                state <= 2'b10;        // DATA
            end

            2'b10: // DATA
            begin
                busy <= 1;
                tx <= data_reg[bit_count];

                if (bit_count == 3'd7)
                begin
                    state <= 2'b11;    // STOP
                end
                else
                begin
                    bit_count <= bit_count + 1;
                end
            end
            2'b11: // STOP
            begin
                busy <= 1; // you're not done until IDLE
                tx <= 1;
                state <= 2'b00;   // IDLE
            end
        endcase
    end
end

endmodule

uart_tb.v
`timescale 1ns/1ps  // define time units and precision

module uart_tx_tb;  // define module

reg clk;            // define our signals (inputs can be initialized by TB)
reg reset;          // (outputs are signals driven by the hardware)
reg start;
reg [7:0] data;

wire tx;
wire busy;

// Instantiate from other module
uart_tx uut(
    .clk(clk),
    .reset(reset),
    .start(start),
    .data(data),
    .tx(tx),
    .busy(busy)
);

// Generate the Clock
always
begin
    #5 clk = ~clk;
end

// Set up the inputs and Simulation Details
initial
begin
    clk = 0;
    reset = 1;
    start = 0;
    data = 8'b10100110;

    $dumpfile("uart_tx.vcd");
    $dumpvars(0, uart_tx_tb);

    #10;
    reset = 0;

    // TODO: Start a transmission
    #10;
    start = 1;

    #10;
    start = 0;

    #100;       
    $finish;
end


// Check my work (Verifies Time, State, Bit, Tx, Busy states)
initial
begin
    $monitor(
        "Time=%0t State=%b Bit=%d TX=%b Busy=%b",
        $time,
        uut.state,
        uut.bit_count,
        tx,
        busy
    );
end
endmodule

uart_tx.vcd
$date
	Tue Jul 21 03:08:56 2026
$end
$version
	Icarus Verilog
$end
$timescale
	1ps
$end
$scope module uart_tx_tb $end
$var wire 1 ! tx $end
$var wire 1 " busy $end
$var reg 1 # clk $end
$var reg 8 $ data [7:0] $end
$var reg 1 % reset $end
$var reg 1 & start $end
$scope module uut $end
$var wire 1 # clk $end
$var wire 8 ' data [7:0] $end
$var wire 1 % reset $end
$var wire 1 & start $end
$var reg 3 ( bit_count [2:0] $end
$var reg 1 " busy $end
$var reg 8 ) data_reg [7:0] $end
$var reg 2 * state [1:0] $end
$var reg 1 ! tx $end
$upscope $end
$upscope $end
$enddefinitions $end
$comment Show the parameter values. $end
$dumpall
$end
#0
$dumpvars
bx *
bx )
bx (
b10100110 '
0&
1%
b10100110 $
0#
x"
x!
$end
#5000
b0 )
b0 (
1!
0"
b0 *
1#
#10000
0#
0%
#15000
1#
#20000
0#
1&
#25000
0!
b1 *
b10100110 )
1"
1#
#30000
0#
0&
#35000
b10 *
1#
#40000
0#
#45000
b1 (
1#
#50000
0#
#55000
b10 (
1!
1#
#60000
0#
#65000
b11 (
1#
#70000
0#
#75000
b100 (
0!
1#
#80000
0#
#85000
b101 (
1#
#90000
0#
#95000
b110 (
1!
1#
#100000
0#
#105000
b111 (
0!
1#
#110000
0#
#115000
b11 *
1!
1#
#120000
0#
#125000
b0 *
1#
