UART/uart_polished.v
module uart_tx (
    input clk,              // things we define in TB like here clk = 0 so clk start at 0 (low)
    input reset,
    input start,
    input [7:0] data,           // interesting enough GTKWave keeps this value in hexadecimal

    output reg tx,              // changes with the respective bits being sent in low = 0 and high = 1, note it reads the opposite way when starts with looking at [0] index
    output reg busy             // turns on when start and turns off (goes low) when starts over at IDLE again
);

// internal stuff we do not want to see in GTKWave

reg [7:0] display_reg;      // where we store data like what we defined in tb data = 8'b........ 
reg [2:0] bit_counter;      // keep track of how many bits are sent to tx (helps us move to STOP state)
reg [1:0] state;

// the FSM Process (IDLE, Start, Data, Stop) - its very important to keep my code organized

always @(posedge clk)
begin
    if (reset)      // IDLE
        begin
            state <= 2'b00;
            busy <= 0;
            tx <= 1;
            bit_counter <= 3'b000;
            display_reg <= 8'b0;
        end

    else
        begin
            case (state)    
                2'b00:              // IDLE
                begin
                    busy <= 0;
                    tx <= 1;
                    if (start)      // until not IDLE - data gets stored in display_reg and transitions to START state begins here...
                    begin
                        busy <= 1;
                        tx <= 0;
                        bit_counter <= 3'b000;
                        state <= 2'b01;
                        display_reg <= data;       // load in data
                    end
                end

                2'b01:              // START - we can start transmitting now and move to data. Wonder what that will do...
                begin
                    busy <= 1;
                    tx <= 0;
                    state <= 2'b10;
                end

                2'b10:              // DATA - remember when we stored our data? Now we get to transmit it!
                begin
                    busy <= 1;
                    tx <= display_reg[bit_counter];
                    if (bit_counter == 3'd7)            // checks when all the data is transmitted. If confirmed, we get to move to the next state... the STOP state!!!
                    begin
                        state <= 2'b11;
                    end
                    else                                // this says we're not done transmitted so transmit the next bit
                    begin
                        bit_counter <= bit_counter + 1;
                    end
                end
                
                2'b11:             // STOP state - prepare to go back to IDLE, no more transmission. Mission Complete - round 2...
                begin
                    busy <= 0;     
                    tx <= 1;
                    state <= 2'b00;
                end
            endcase
        end
    end
endmodule

UART/uart_tb_polished.v
`timescale 1ns/1ps

module uart_tx_tb;

    reg clk;              // signals that I'm going to define very soon
    reg reset;
    reg start;
    reg [7:0] data;

    wire tx;              // things that change as a result of the TB definition
    wire busy;

uart_tx uut(
    .clk(clk),              // assign pin from uart_polished.v (.clk) to the signal (clk) I defined here. Simulation won't work unless I do this
    .reset(reset),
    .start(start),
    .data(data),
    .tx(tx),
    .busy(busy)
);

always
begin                       // we need a clock so this builds it. full clock cycle is 10 time units and ~clk inverts clk each 5 time units
    #5 clk = ~clk;
end

initial
begin                       // this is the important stuff to make our uart_polished.v work
    start = 0;              // definitions (remember I mentioned those earlier?)
    reset = 1;
    clk = 0;
    data = 8'b10101101;

    $dumpfile("bananas.vcd");           // this gives us our GTKWave file name, shows it can be arbitrary haha!
    $dumpvars(0, uart_tx_tb);           // important when we compile and do vvp uart_tx_tb (sound familiar?) gives us all our cool monitor data!

    #10;
    reset = 0;                          // lets us get out of reset
    #10;
    start = 1;                          // lets us start the if(start) part of the other file, AKA lets us escape IDLE
    #10;
    start = 0;                          // lets us move to other states and does not mess up our simulation when we need to start over again

    #120;                             // arbitrary number - I wanted to make sure this simulation had enough time to fully run through
                                        // (although, it was helpful to see it successfully looping again after STOP, shows my code is good)
    $finish;
end


// Check my work (Verifies Time, State, Bit, Tx, Busy states)
// I call this with vvp uart_tx_tb (sound familiar?)
initial
begin
    $monitor(
        "Time=%0t State=%b Bit=%d TX=%b Busy=%b",
        $time,
        uut.state,
        uut.bit_counter,
        tx,
        busy
    );
end
endmodule

UART/bananas.vcd
$date
	Tue Jul 21 23:57:18 2026
$end
$version
	Icarus Verilog
$end
$timescale
	1ps
$end
$scope module uart_tx_tb $end
$var wire 1 ! tx $end
$var wire 1 " busy $end
$var reg 1 # clk $end
$var reg 8 $ data [7:0] $end
$var reg 1 % reset $end
$var reg 1 & start $end
$scope module uut $end
$var wire 1 # clk $end
$var wire 8 ' data [7:0] $end
$var wire 1 % reset $end
$var wire 1 & start $end
$var reg 3 ( bit_counter [2:0] $end
$var reg 1 " busy $end
$var reg 8 ) display_reg [7:0] $end
$var reg 2 * state [1:0] $end
$var reg 1 ! tx $end
$upscope $end
$upscope $end
$enddefinitions $end
$comment Show the parameter values. $end
$dumpall
$end
#0
$dumpvars
bx *
bx )
bx (
b10101101 '
0&
1%
b10101101 $
0#
x"
x!
$end
#5000
b0 )
b0 (
1!
0"
b0 *
1#
#10000
0#
0%
#15000
1#
#20000
0#
1&
#25000
b10101101 )
b1 *
0!
1"
1#
#30000
0#
0&
#35000
b10 *
1#
#40000
0#
#45000
b1 (
1!
1#
#50000
0#
#55000
b10 (
0!
1#
#60000
0#
#65000
b11 (
1!
1#
#70000
0#
#75000
b100 (
1#
#80000
0#
#85000
b101 (
0!
1#
#90000
0#
#95000
b110 (
1!
1#
#100000
0#
#105000
b111 (
0!
1#
#110000
0#
#115000
b11 *
1!
1#
#120000
0#
#125000
b0 *
0"
1#
